multidim_galerkin_pod/__init__.py
multidim_galerkin_pod/chaos_expansion_utils.py
multidim_galerkin_pod/gen_pod_utils.py
multidim_galerkin_pod/ldfnp_ext_cholmod.py
multidim_galerkin_pod/mock_ext_cholmod.py
multidim_galerkin_pod/ten_sor_utils.py
multidim_galerkin_pod-1.1.3.dist-info/AUTHORS
multidim_galerkin_pod-1.1.3.dist-info/METADATA
multidim_galerkin_pod-1.1.3.dist-info/WHEEL
multidim_galerkin_pod-1.1.3.dist-info/pbr.json
multidim_galerkin_pod-1.1.3.dist-info/top_level.txt
multidim_galerkin_pod-1.1.3.dist-info/RECORD
